setup.py
pysfx/__init__.py
pysfx/b64reader.py
pysfx/gzipreader.py
pysfx/pysfx.py
pysfx/pysfxcreator.py
pysfx/unpack.py
pysfx.egg-info/PKG-INFO
pysfx.egg-info/SOURCES.txt
pysfx.egg-info/dependency_links.txt
pysfx.egg-info/requires.txt
pysfx.egg-info/top_level.txt
script/pysfx