Metadata-Version: 1.0
Name: pysfx
Version: 0.1
Summary: Tool for creating self-extracting Python scripts with autorun.
Home-page: http://www.cryto.net/projects/pysfx/
Author: Sven Slootweg
Author-email: admin@cryto.net
License: UNKNOWN
Platform: UNKNOWN
